clip_bbox/__init__.py
clip_bbox/__main__.py
clip_bbox/bbox_utils.py
clip_bbox/clip.py
clip_bbox/clip_model_setup.py
clip_bbox/clipbbox.py
clip_bbox/model.py
clip_bbox/newpad.py
clip_bbox/preprocess.py
clip_bbox/simple_tokenizer.py
clip_bbox/tests/test_all.py
clip_bbox/tests/assets/camera.png
clip_bbox/tests/assets/heat.npz
clip_bbox/tests/assets/rocket.npy
clip_bbox/tests/assets/rocket.png
clip_bbox/tests/assets/test_all-gt_camera.png
clip_bbox/tests/assets/test_all-gt_rocket.png
clip_bbox/tests/assets/test_img_heat_bbox_disp-gt_output.png
clip_bbox-0.3.1.dist-info/LICENSE
clip_bbox-0.3.1.dist-info/METADATA
clip_bbox-0.3.1.dist-info/WHEEL
clip_bbox-0.3.1.dist-info/top_level.txt
clip_bbox-0.3.1.dist-info/RECORD
